{
    "version": "https://jsonfeed.org/version/1",
    "title": "Analytics repositories",
    "home_page_url": "https://github.com/search?o=desc&q=analytics+language%3Ajavascript+language%3Atypescript+sort%3Aupdated-desc&s=updated&type=Repositories",
    "feed_url": "https://davidwells.github.io/github-search-rss/analytics-javascript-repo.json",
    "description": "Analytics repositories on GitHub",
    "items": [
        {
            "content_html": "<img src=\"https://avatars.githubusercontent.com/u/60279149?v=4\" width=\"64\" height=\"64\" alt=\"\"/><br/><div>Opdex Platform UI connecting to Opdex Platform API and Opdex Protocols for decentralized analytics and transactional quotes.</div>",
            "url": "https://github.com/Opdex/opdex-v1-ui",
            "title": "Opdex/opdex-v1-ui: Opdex Platform UI connecting to Opdex Platform API and Opdex Protocols for decentralized analytics and transactional quotes.",
            "date_modified": "2022-01-11T03:21:33.000Z",
            "date_published": "2020-12-01T06:35:06.000Z",
            "author": {
                "name": "Opdex",
                "url": "https://github.com/Opdex"
            }
        },
        {
            "content_html": "<img src=\"https://avatars.githubusercontent.com/u/41077760?v=4\" width=\"64\" height=\"64\" alt=\"\"/><br/><div>The AWS Amplify CLI is a toolchain for simplifying serverless web and mobile development.</div>",
            "url": "https://github.com/aws-amplify/amplify-cli",
            "title": "aws-amplify/amplify-cli: The AWS Amplify CLI is a toolchain for simplifying serverless web and mobile development.",
            "date_modified": "2022-05-05T12:39:46.000Z",
            "date_published": "2018-08-23T16:33:10.000Z",
            "author": {
                "name": "aws-amplify",
                "url": "https://github.com/aws-amplify"
            }
        },
        {
            "content_html": "<img src=\"https://avatars.githubusercontent.com/u/1494564?v=4\" width=\"64\" height=\"64\" alt=\"\"/><br/><div>Universal Analytics Payload Parser</div>",
            "url": "https://github.com/thyngster/universal-analytics-payload-parser",
            "title": "thyngster/universal-analytics-payload-parser: Universal Analytics Payload Parser",
            "date_modified": "2022-04-27T14:02:01.000Z",
            "date_published": "2022-04-24T21:18:13.000Z",
            "author": {
                "name": "thyngster",
                "url": "https://github.com/thyngster"
            }
        },
        {
            "content_html": "<img src=\"https://avatars.githubusercontent.com/u/103216230?u=542f651acfe696879c4976c0ab9b30dc30785bd3&v=4\" width=\"64\" height=\"64\" alt=\"\"/><br/><div>Blockchain Marketplace, Swapping and Analytics </div>",
            "url": "https://github.com/iebgit/cypherswap",
            "title": "iebgit/cypherswap: Blockchain Marketplace, Swapping and Analytics ",
            "date_modified": "2022-05-06T00:33:53.000Z",
            "date_published": "2022-04-26T00:57:47.000Z",
            "author": {
                "name": "iebgit",
                "url": "https://github.com/iebgit"
            }
        },
        {
            "content_html": "<img src=\"https://avatars.githubusercontent.com/u/95447968?u=0d637ecd9a80b29afed854654ad0172078a199fd&v=4\" width=\"64\" height=\"64\" alt=\"\"/><br/><div>React client to access the Web Analytics Service Project. </div>",
            "url": "https://github.com/dom-gallo/Web-Analytics-Client",
            "title": "dom-gallo/Web-Analytics-Client: React client to access the Web Analytics Service Project. ",
            "date_modified": "2022-05-01T15:39:05.000Z",
            "date_published": "2022-04-25T01:45:19.000Z",
            "author": {
                "name": "dom-gallo",
                "url": "https://github.com/dom-gallo"
            }
        },
        {
            "content_html": "<img src=\"https://avatars.githubusercontent.com/u/88215783?v=4\" width=\"64\" height=\"64\" alt=\"\"/><br/><div>Swetrix Analytics API</div>",
            "url": "https://github.com/Swetrix/swetrix-api",
            "title": "Swetrix/swetrix-api: Swetrix Analytics API",
            "date_modified": "2022-05-05T15:38:29.000Z",
            "date_published": "2021-03-18T21:55:22.000Z",
            "author": {
                "name": "Swetrix",
                "url": "https://github.com/Swetrix"
            }
        },
        {
            "content_html": "<img src=\"https://avatars.githubusercontent.com/u/13399086?u=b2808531d17db4cfeea089bdb3c8f5bd97f66276&v=4\" width=\"64\" height=\"64\" alt=\"\"/><br/><div>A demonstration of a concept for  Uganda national census analytics and reports automation</div>",
            "url": "https://github.com/vexa256/Census-Analytics",
            "title": "vexa256/Census-Analytics: A demonstration of a concept for  Uganda national census analytics and reports automation",
            "date_modified": "2022-05-06T20:37:05.000Z",
            "date_published": "2022-05-06T20:25:37.000Z",
            "author": {
                "name": "vexa256",
                "url": "https://github.com/vexa256"
            }
        },
        {
            "content_html": "<img src=\"https://avatars.githubusercontent.com/u/60195163?v=4\" width=\"64\" height=\"64\" alt=\"\"/><br/><div></div>",
            "url": "https://github.com/tankpit-analytics/tankpit-analytics.github.io",
            "title": "tankpit-analytics/tankpit-analytics.github.io",
            "date_modified": "2022-01-10T23:06:14.000Z",
            "date_published": "2020-01-22T18:49:45.000Z",
            "author": {
                "name": "tankpit-analytics",
                "url": "https://github.com/tankpit-analytics"
            }
        },
        {
            "content_html": "<img src=\"https://avatars.githubusercontent.com/u/7195757?v=4\" width=\"64\" height=\"64\" alt=\"\"/><br/><div>The open and composable observability and data visualization platform. Visualize metrics, logs, and traces from multiple sources like Prometheus, Loki, Elasticsearch, InfluxDB, Postgres and many more. </div>",
            "url": "https://github.com/grafana/grafana",
            "title": "grafana/grafana: The open and composable observability and data visualization platform. Visualize metrics, logs, and traces from multiple sources like Prometheus, Loki, Elasticsearch, InfluxDB, Postgres and many more. ",
            "date_modified": "2022-05-07T00:15:21.000Z",
            "date_published": "2013-12-11T15:59:56.000Z",
            "author": {
                "name": "grafana",
                "url": "https://github.com/grafana"
            }
        },
        {
            "content_html": "<img src=\"https://avatars.githubusercontent.com/u/38541875?v=4\" width=\"64\" height=\"64\" alt=\"\"/><br/><div>Insights Explorer is a tool to catalogue and present analytical &amp; research work.</div>",
            "url": "https://github.com/ExpediaGroup/insights-explorer",
            "title": "ExpediaGroup/insights-explorer: Insights Explorer is a tool to catalogue and present analytical & research work.",
            "date_modified": "2022-03-02T17:14:30.000Z",
            "date_published": "2021-11-30T11:34:13.000Z",
            "author": {
                "name": "ExpediaGroup",
                "url": "https://github.com/ExpediaGroup"
            }
        },
        {
            "content_html": "<img src=\"https://avatars.githubusercontent.com/u/25537372?v=4\" width=\"64\" height=\"64\" alt=\"\"/><br/><div>Application that aims to represent analytics of some decentralized exchanges.</div>",
            "url": "https://github.com/albertobas/dexes-analytics",
            "title": "albertobas/dexes-analytics: Application that aims to represent analytics of some decentralized exchanges.",
            "date_modified": "2022-05-03T22:01:10.000Z",
            "date_published": "2022-05-03T21:32:50.000Z",
            "author": {
                "name": "albertobas",
                "url": "https://github.com/albertobas"
            }
        },
        {
            "content_html": "<img src=\"https://avatars.githubusercontent.com/u/11316520?v=4\" width=\"64\" height=\"64\" alt=\"\"/><br/><div>The analytics blog for the ARPA-E NI4AI project</div>",
            "url": "https://github.com/PingThingsIO/blog",
            "title": "PingThingsIO/blog: The analytics blog for the ARPA-E NI4AI project",
            "date_modified": "2022-03-29T19:50:34.000Z",
            "date_published": "2017-12-18T17:30:17.000Z",
            "author": {
                "name": "PingThingsIO",
                "url": "https://github.com/PingThingsIO"
            }
        },
        {
            "content_html": "<img src=\"https://avatars.githubusercontent.com/u/819518?v=4\" width=\"64\" height=\"64\" alt=\"\"/><br/><div>The next version of AJS</div>",
            "url": "https://github.com/segmentio/analytics-next",
            "title": "segmentio/analytics-next: The next version of AJS",
            "date_modified": "2022-05-05T13:41:06.000Z",
            "date_published": "2020-09-02T16:58:04.000Z",
            "author": {
                "name": "segmentio",
                "url": "https://github.com/segmentio"
            }
        },
        {
            "content_html": "<img src=\"https://avatars.githubusercontent.com/u/41077760?v=4\" width=\"64\" height=\"64\" alt=\"\"/><br/><div>A declarative JavaScript library for application development using cloud services.</div>",
            "url": "https://github.com/aws-amplify/amplify-js",
            "title": "aws-amplify/amplify-js: A declarative JavaScript library for application development using cloud services.",
            "date_modified": "2022-05-06T14:38:33.000Z",
            "date_published": "2017-10-02T22:17:14.000Z",
            "author": {
                "name": "aws-amplify",
                "url": "https://github.com/aws-amplify"
            }
        },
        {
            "content_html": "<img src=\"https://avatars.githubusercontent.com/u/78913720?v=4\" width=\"64\" height=\"64\" alt=\"\"/><br/><div>Plataforma open-source para coleta de dados, processamento, visualização e gerenciamento de dispositivos IoT.</div>",
            "url": "https://github.com/IBTI-DF/Plataforma-Iot",
            "title": "IBTI-DF/Plataforma-Iot: Plataforma open-source para coleta de dados, processamento, visualização e gerenciamento de dispositivos IoT.",
            "date_modified": "2022-05-02T13:10:28.000Z",
            "date_published": "2021-02-18T17:04:45.000Z",
            "author": {
                "name": "IBTI-DF",
                "url": "https://github.com/IBTI-DF"
            }
        },
        {
            "content_html": "<img src=\"https://avatars.githubusercontent.com/u/16785467?v=4\" width=\"64\" height=\"64\" alt=\"\"/><br/><div></div>",
            "url": "https://github.com/googleapis/nodejs-analytics-admin",
            "title": "googleapis/nodejs-analytics-admin",
            "date_modified": "2022-03-28T08:20:18.000Z",
            "date_published": "2020-07-17T20:47:12.000Z",
            "author": {
                "name": "googleapis",
                "url": "https://github.com/googleapis"
            }
        },
        {
            "content_html": "<img src=\"https://avatars.githubusercontent.com/u/80134844?v=4\" width=\"64\" height=\"64\" alt=\"\"/><br/><div>\n<g-emoji class=\"g-emoji\" alias=\"bar_chart\" fallback-src=\"https://github.githubassets.com/images/icons/emoji/unicode/1f4ca.png\">📊</g-emoji> Open source visualization dashboards for OpenSearch.</div>",
            "url": "https://github.com/opensearch-project/OpenSearch-Dashboards",
            "title": "opensearch-project/OpenSearch-Dashboards: 📊 Open source visualization dashboards for OpenSearch.",
            "date_modified": "2022-05-06T19:09:57.000Z",
            "date_published": "2021-01-29T22:10:13.000Z",
            "author": {
                "name": "opensearch-project",
                "url": "https://github.com/opensearch-project"
            }
        },
        {
            "content_html": "<img src=\"https://avatars.githubusercontent.com/u/16785467?v=4\" width=\"64\" height=\"64\" alt=\"\"/><br/><div></div>",
            "url": "https://github.com/googleapis/nodejs-analytics-data",
            "title": "googleapis/nodejs-analytics-data",
            "date_modified": "2022-05-03T05:02:27.000Z",
            "date_published": "2020-09-01T23:06:01.000Z",
            "author": {
                "name": "googleapis",
                "url": "https://github.com/googleapis"
            }
        },
        {
            "content_html": "<img src=\"https://avatars.githubusercontent.com/u/16785467?v=4\" width=\"64\" height=\"64\" alt=\"\"/><br/><div>Node.js client for Google Cloud BigQuery: A fast, economical and fully-managed enterprise data warehouse for large-scale data analytics.</div>",
            "url": "https://github.com/googleapis/nodejs-bigquery",
            "title": "googleapis/nodejs-bigquery: Node.js client for Google Cloud BigQuery: A fast, economical and fully-managed enterprise data warehouse for large-scale data analytics.",
            "date_modified": "2022-05-06T14:29:03.000Z",
            "date_published": "2017-07-26T20:27:38.000Z",
            "author": {
                "name": "googleapis",
                "url": "https://github.com/googleapis"
            }
        },
        {
            "content_html": "<img src=\"https://avatars.githubusercontent.com/u/819518?v=4\" width=\"64\" height=\"64\" alt=\"\"/><br/><div>The hassle-free way to add analytics to your React-Native app.</div>",
            "url": "https://github.com/segmentio/analytics-react-native",
            "title": "segmentio/analytics-react-native: The hassle-free way to add analytics to your React-Native app.",
            "date_modified": "2022-05-06T09:50:08.000Z",
            "date_published": "2018-08-11T21:58:35.000Z",
            "author": {
                "name": "segmentio",
                "url": "https://github.com/segmentio"
            }
        }
    ]
}