{
    "version": "https://jsonfeed.org/version/1",
    "title": "Cognito repositories",
    "home_page_url": "https://github.com/search?o=desc&q=cognito+language%3Ajavascript+language%3Atypescript+sort%3Aupdated-desc&s=updated&type=Repositories",
    "feed_url": "https://davidwells.github.io/github-search-rss/cognito-javascript-repo.json",
    "description": "Cognito repositories on GitHub",
    "items": [
        {
            "content_html": "<img src=\"https://avatars.githubusercontent.com/u/92384?v=4\" width=\"64\" height=\"64\" alt=\"\"/><br/><div></div>",
            "url": "https://github.com/developmentseed/cognito_client",
            "title": "developmentseed/cognito_client",
            "date_modified": "2022-10-27T08:20:37.000Z",
            "date_published": "2022-10-26T18:45:01.000Z",
            "author": {
                "name": "developmentseed",
                "url": "https://github.com/developmentseed"
            }
        },
        {
            "content_html": "<img src=\"https://avatars.githubusercontent.com/u/703354?v=4\" width=\"64\" height=\"64\" alt=\"\"/><br/><div>CloudFront authorization with Cognito for CDK</div>",
            "url": "https://github.com/henrist/cdk-cloudfront-auth",
            "title": "henrist/cdk-cloudfront-auth: CloudFront authorization with Cognito for CDK",
            "date_modified": "2022-10-12T16:26:47.000Z",
            "date_published": "2020-07-11T01:58:54.000Z",
            "author": {
                "name": "henrist",
                "url": "https://github.com/henrist"
            }
        },
        {
            "content_html": "<img src=\"https://avatars.githubusercontent.com/u/100313416?u=479e354f98ac13b90479074a43b5d9254a529548&v=4\" width=\"64\" height=\"64\" alt=\"\"/><br/><div>The bare bones of cognito identity only needing the clientId</div>",
            "url": "https://github.com/nicksaravia/cognito-identity-mini",
            "title": "nicksaravia/cognito-identity-mini: The bare bones of cognito identity only needing the clientId",
            "date_modified": "2022-10-29T02:50:50.000Z",
            "date_published": "2022-10-29T02:45:10.000Z",
            "author": {
                "name": "nicksaravia",
                "url": "https://github.com/nicksaravia"
            }
        },
        {
            "content_html": "<img src=\"https://avatars.githubusercontent.com/u/57479106?v=4\" width=\"64\" height=\"64\" alt=\"\"/><br/><div></div>",
            "url": "https://github.com/dayookubanjo/django-aws-cognito-social-login",
            "title": "dayookubanjo/django-aws-cognito-social-login",
            "date_modified": "2022-10-29T14:54:50.000Z",
            "date_published": "2022-10-29T14:54:30.000Z",
            "author": {
                "name": "dayookubanjo",
                "url": "https://github.com/dayookubanjo"
            }
        },
        {
            "content_html": "<img src=\"https://avatars.githubusercontent.com/u/52230505?u=c95bdc16483ea4eabffd0c18fe7068c8b41ad483&v=4\" width=\"64\" height=\"64\" alt=\"\"/><br/><div></div>",
            "url": "https://github.com/naru200/cday-2022-cognito-example",
            "title": "naru200/cday-2022-cognito-example",
            "date_modified": "2022-10-25T02:05:05.000Z",
            "date_published": "2022-10-25T02:02:33.000Z",
            "author": {
                "name": "naru200",
                "url": "https://github.com/naru200"
            }
        },
        {
            "content_html": "<img src=\"https://avatars.githubusercontent.com/u/12545474?u=85f8a003c10c312e2d0b93f78a2a15f98f61bbe4&v=4\" width=\"64\" height=\"64\" alt=\"\"/><br/><div></div>",
            "url": "https://github.com/rshaiju/cognito-pocs",
            "title": "rshaiju/cognito-pocs",
            "date_modified": "2022-10-29T03:18:42.000Z",
            "date_published": "2022-10-29T03:14:48.000Z",
            "author": {
                "name": "rshaiju",
                "url": "https://github.com/rshaiju"
            }
        },
        {
            "content_html": "<img src=\"https://avatars.githubusercontent.com/u/41077760?v=4\" width=\"64\" height=\"64\" alt=\"\"/><br/><div>A declarative JavaScript library for application development using cloud services.</div>",
            "url": "https://github.com/aws-amplify/amplify-js",
            "title": "aws-amplify/amplify-js: A declarative JavaScript library for application development using cloud services.",
            "date_modified": "2022-10-29T23:11:32.000Z",
            "date_published": "2017-10-02T22:17:14.000Z",
            "author": {
                "name": "aws-amplify",
                "url": "https://github.com/aws-amplify"
            }
        },
        {
            "content_html": "<img src=\"https://avatars.githubusercontent.com/u/9872839?v=4\" width=\"64\" height=\"64\" alt=\"\"/><br/><div></div>",
            "url": "https://github.com/Lokicoule/nestjs-cognito",
            "title": "Lokicoule/nestjs-cognito",
            "date_modified": "2022-10-08T11:12:06.000Z",
            "date_published": "2022-07-22T13:36:19.000Z",
            "author": {
                "name": "Lokicoule",
                "url": "https://github.com/Lokicoule"
            }
        },
        {
            "content_html": "<img src=\"https://avatars.githubusercontent.com/u/8931462?v=4\" width=\"64\" height=\"64\" alt=\"\"/><br/><div>Serverless reference application on AWS</div>",
            "url": "https://github.com/aws-samples/dotnet-serverless-imagerecognition",
            "title": "aws-samples/dotnet-serverless-imagerecognition: Serverless reference application on AWS",
            "date_modified": "2022-10-28T22:47:33.000Z",
            "date_published": "2021-07-22T17:09:21.000Z",
            "author": {
                "name": "aws-samples",
                "url": "https://github.com/aws-samples"
            }
        },
        {
            "content_html": "<img src=\"https://avatars.githubusercontent.com/u/103588961?u=e4b43223d33d3dcfb27be798f5273c80e52d0419&v=4\" width=\"64\" height=\"64\" alt=\"\"/><br/><div>AWS Cognito Implementation</div>",
            "url": "https://github.com/cesarsunrise/aws-cognito-implementation",
            "title": "cesarsunrise/aws-cognito-implementation: AWS Cognito Implementation",
            "date_modified": "2022-10-28T20:42:36.000Z",
            "date_published": "2022-10-28T19:59:33.000Z",
            "author": {
                "name": "cesarsunrise",
                "url": "https://github.com/cesarsunrise"
            }
        },
        {
            "content_html": "<img src=\"https://avatars.githubusercontent.com/u/85178973?u=a9d3ec78be9f4d93d3c6a6f23354f1e6753be850&v=4\" width=\"64\" height=\"64\" alt=\"\"/><br/><div>Aws Cognito Spring Java Client</div>",
            "url": "https://github.com/christoferson/aws-cognito-java-spring",
            "title": "christoferson/aws-cognito-java-spring: Aws Cognito Spring Java Client",
            "date_modified": "2021-10-08T01:13:38.000Z",
            "date_published": "2021-10-06T07:27:59.000Z",
            "author": {
                "name": "christoferson",
                "url": "https://github.com/christoferson"
            }
        },
        {
            "content_html": "<img src=\"https://avatars.githubusercontent.com/u/48167381?u=a2443486eddc2c54efc944b0731498fd3aab372d&v=4\" width=\"64\" height=\"64\" alt=\"\"/><br/><div>Backend to be used in the Touch Sistemas project</div>",
            "url": "https://github.com/gugazimmermann/touch-admin",
            "title": "gugazimmermann/touch-admin: Backend to be used in the Touch Sistemas project",
            "date_modified": "2022-09-30T16:12:47.000Z",
            "date_published": "2022-09-30T16:10:11.000Z",
            "author": {
                "name": "gugazimmermann",
                "url": "https://github.com/gugazimmermann"
            }
        },
        {
            "content_html": "<img src=\"https://avatars.githubusercontent.com/u/20050863?v=4\" width=\"64\" height=\"64\" alt=\"\"/><br/><div>AWS Cognito package using the AWS SDK for PHP/Laravel</div>",
            "url": "https://github.com/ellaisys/aws-cognito",
            "title": "ellaisys/aws-cognito: AWS Cognito package using the AWS SDK for PHP/Laravel",
            "date_modified": "2022-10-18T23:22:02.000Z",
            "date_published": "2020-08-31T18:27:10.000Z",
            "author": {
                "name": "ellaisys",
                "url": "https://github.com/ellaisys"
            }
        },
        {
            "content_html": "<img src=\"https://avatars.githubusercontent.com/u/8931462?v=4\" width=\"64\" height=\"64\" alt=\"\"/><br/><div>AWS CDK for Discourse</div>",
            "url": "https://github.com/aws-samples/aws-cdk-for-discourse",
            "title": "aws-samples/aws-cdk-for-discourse: AWS CDK for Discourse",
            "date_modified": "2022-10-28T15:27:32.000Z",
            "date_published": "2022-10-10T18:24:20.000Z",
            "author": {
                "name": "aws-samples",
                "url": "https://github.com/aws-samples"
            }
        },
        {
            "content_html": "<img src=\"https://avatars.githubusercontent.com/u/3299148?v=4\" width=\"64\" height=\"64\" alt=\"\"/><br/><div>JS library for verifying JWTs signed by Amazon Cognito, and any OIDC-compatible IDP that signs JWTs with RS256, RS384, and RS512</div>",
            "url": "https://github.com/awslabs/aws-jwt-verify",
            "title": "awslabs/aws-jwt-verify: JS library for verifying JWTs signed by Amazon Cognito, and any OIDC-compatible IDP that signs JWTs with RS256, RS384, and RS512",
            "date_modified": "2022-10-26T10:31:18.000Z",
            "date_published": "2021-09-16T15:53:42.000Z",
            "author": {
                "name": "awslabs",
                "url": "https://github.com/awslabs"
            }
        },
        {
            "content_html": "<img src=\"https://avatars.githubusercontent.com/u/108342279?v=4\" width=\"64\" height=\"64\" alt=\"\"/><br/><div>AWS AppSync GraphQL API that uses AWS DynamoDB as a datasource and AWS Cognito for authentification made with Serverless framework</div>",
            "url": "https://github.com/NikolaGospodjinacki1/ServerlessFrameworkAppSyncAPI",
            "title": "NikolaGospodjinacki1/ServerlessFrameworkAppSyncAPI: AWS AppSync GraphQL API that uses AWS DynamoDB as a datasource and AWS Cognito for authentification made with Serverless framework",
            "date_modified": "2022-10-29T13:51:04.000Z",
            "date_published": "2022-10-17T08:36:54.000Z",
            "author": {
                "name": "NikolaGospodjinacki1",
                "url": "https://github.com/NikolaGospodjinacki1"
            }
        },
        {
            "content_html": "<img src=\"https://avatars.githubusercontent.com/u/54841207?v=4\" width=\"64\" height=\"64\" alt=\"\"/><br/><div></div>",
            "url": "https://github.com/yohioy/masteryo-cognito",
            "title": "yohioy/masteryo-cognito",
            "date_modified": "2022-10-04T16:08:42.000Z",
            "date_published": "2020-06-02T09:40:36.000Z",
            "author": {
                "name": "yohioy",
                "url": "https://github.com/yohioy"
            }
        },
        {
            "content_html": "<img src=\"https://avatars.githubusercontent.com/u/19799501?u=b7d6c4b18bc0a7afa1b793b524557cc007b69002&v=4\" width=\"64\" height=\"64\" alt=\"\"/><br/><div></div>",
            "url": "https://github.com/cjm2021401/CognitoExample",
            "title": "cjm2021401/CognitoExample",
            "date_modified": "2022-10-28T03:47:03.000Z",
            "date_published": "2022-10-28T03:46:08.000Z",
            "author": {
                "name": "cjm2021401",
                "url": "https://github.com/cjm2021401"
            }
        },
        {
            "content_html": "<img src=\"https://avatars.githubusercontent.com/u/91928389?u=ea9ecb8daa33a5534f196b1ed4d1144bd8a23e71&v=4\" width=\"64\" height=\"64\" alt=\"\"/><br/><div></div>",
            "url": "https://github.com/sssalim-aws/Multilayered_API_Security_with_Cognito_and_WAF",
            "title": "sssalim-aws/Multilayered_API_Security_with_Cognito_and_WAF",
            "date_modified": "2022-10-21T13:20:45.000Z",
            "date_published": "2022-09-22T02:56:59.000Z",
            "author": {
                "name": "sssalim-aws",
                "url": "https://github.com/sssalim-aws"
            }
        },
        {
            "content_html": "<img src=\"https://avatars.githubusercontent.com/u/1867845?u=2dd0ed02c05ee12f61ffad32e3683ddeaf124c0f&v=4\" width=\"64\" height=\"64\" alt=\"\"/><br/><div></div>",
            "url": "https://github.com/poad/github-cognito-oidc-proxy",
            "title": "poad/github-cognito-oidc-proxy",
            "date_modified": "2022-09-04T01:36:08.000Z",
            "date_published": "2022-08-30T22:01:29.000Z",
            "author": {
                "name": "poad",
                "url": "https://github.com/poad"
            }
        }
    ]
}