{
    "version": "https://jsonfeed.org/version/1",
    "title": "Cognito repositories",
    "home_page_url": "https://github.com/search?o=desc&q=cognito+language%3Ajavascript+language%3Atypescript+sort%3Aupdated-desc&s=updated&type=Repositories",
    "feed_url": "https://davidwells.github.io/github-search-rss/cognito-javascript-repo.json",
    "description": "Cognito repositories on GitHub",
    "items": [
        {
            "content_html": "<img src=\"https://avatars.githubusercontent.com/u/477051?u=87989d82bd0522c6221fc1306a35160cdf38bae0&v=4\" width=\"64\" height=\"64\" alt=\"\"/><br/><div></div>",
            "url": "https://github.com/tknzk/cognito-sandbox",
            "title": "tknzk/cognito-sandbox",
            "date_modified": "2022-01-11T00:20:35.000Z",
            "date_published": "2017-11-02T03:54:21.000Z",
            "author": {
                "name": "tknzk",
                "url": "https://github.com/tknzk"
            }
        },
        {
            "content_html": "<img src=\"https://avatars.githubusercontent.com/u/26760571?u=70ed69fa4309f3e169a31a95a9f89032c00f96ae&v=4\" width=\"64\" height=\"64\" alt=\"\"/><br/><div></div>",
            "url": "https://github.com/erezrokah/serverless-cognito-triggers",
            "title": "erezrokah/serverless-cognito-triggers",
            "date_modified": "2022-01-10T01:32:50.000Z",
            "date_published": "2019-08-11T14:49:05.000Z",
            "author": {
                "name": "erezrokah",
                "url": "https://github.com/erezrokah"
            }
        },
        {
            "content_html": "<img src=\"https://avatars.githubusercontent.com/u/1867845?u=f70dc290bce8da25d0e5e316fdbb602ab6ff6c99&v=4\" width=\"64\" height=\"64\" alt=\"\"/><br/><div></div>",
            "url": "https://github.com/poad/github-cognito-oidc-proxy",
            "title": "poad/github-cognito-oidc-proxy",
            "date_modified": "2022-09-04T01:36:08.000Z",
            "date_published": "2022-08-30T22:01:29.000Z",
            "author": {
                "name": "poad",
                "url": "https://github.com/poad"
            }
        },
        {
            "content_html": "<img src=\"https://avatars.githubusercontent.com/u/6194359?u=f163e450034a502dd4e2920c707f700df364e969&v=4\" width=\"64\" height=\"64\" alt=\"\"/><br/><div>Terraform module to create Amazon Cognito User Pools, configure its attributes and resources such as app clients, domain, resource servers. Amazon Cognito User Pools provide a secure user directory that scales to hundreds of millions of users.</div>",
            "url": "https://github.com/lgallard/terraform-aws-cognito-user-pool",
            "title": "lgallard/terraform-aws-cognito-user-pool: Terraform module to create Amazon Cognito User Pools, configure its attributes and resources such as app clients, domain, resource servers. Amazon Cognito User Pools provide a secure user directory that scales to hundreds of millions of users.",
            "date_modified": "2022-11-10T03:23:17.000Z",
            "date_published": "2019-10-30T20:54:17.000Z",
            "author": {
                "name": "lgallard",
                "url": "https://github.com/lgallard"
            }
        },
        {
            "content_html": "<img src=\"https://avatars.githubusercontent.com/u/85178973?u=a9d3ec78be9f4d93d3c6a6f23354f1e6753be850&v=4\" width=\"64\" height=\"64\" alt=\"\"/><br/><div>AWS Cognito Client JS</div>",
            "url": "https://github.com/christoferson/aws-cognito-client-js",
            "title": "christoferson/aws-cognito-client-js: AWS Cognito Client JS",
            "date_modified": "2022-10-17T14:09:14.000Z",
            "date_published": "2022-10-17T13:13:52.000Z",
            "author": {
                "name": "christoferson",
                "url": "https://github.com/christoferson"
            }
        },
        {
            "content_html": "<img src=\"https://avatars.githubusercontent.com/u/9872839?v=4\" width=\"64\" height=\"64\" alt=\"\"/><br/><div>AWS Cognito utilities module for NestJS.</div>",
            "url": "https://github.com/Lokicoule/nestjs-cognito",
            "title": "Lokicoule/nestjs-cognito: AWS Cognito utilities module for NestJS.",
            "date_modified": "2022-12-04T15:07:45.000Z",
            "date_published": "2022-07-22T13:36:19.000Z",
            "author": {
                "name": "Lokicoule",
                "url": "https://github.com/Lokicoule"
            }
        },
        {
            "content_html": "<img src=\"https://avatars.githubusercontent.com/u/77633603?v=4\" width=\"64\" height=\"64\" alt=\"\"/><br/><div><g-emoji class=\"g-emoji\" alias=\"lock\" fallback-src=\"https://github.githubassets.com/images/icons/emoji/unicode/1f512.png\">🔒</g-emoji> Py-MultiAuth - The ultimate Python Authentication toolkit (Basic, OAuth, GraphQL, REST, AWS, Cognito…) <g-emoji class=\"g-emoji\" alias=\"lock\" fallback-src=\"https://github.githubassets.com/images/icons/emoji/unicode/1f512.png\">🔒</g-emoji></div>",
            "url": "https://github.com/Escape-Technologies/py-multiauth",
            "title": "Escape-Technologies/py-multiauth: 🔒 Py-MultiAuth - The ultimate Python Authentication toolkit (Basic, OAuth, GraphQL, REST, AWS, Cognito…) 🔒",
            "date_modified": "2022-12-04T11:55:45.000Z",
            "date_published": "2022-06-08T09:50:21.000Z",
            "author": {
                "name": "Escape-Technologies",
                "url": "https://github.com/Escape-Technologies"
            }
        },
        {
            "content_html": "<img src=\"https://avatars.githubusercontent.com/u/124808?u=b54d3e6f554c27d813c3e9bfd26fb7f1aaf9f5ab&v=4\" width=\"64\" height=\"64\" alt=\"\"/><br/><div></div>",
            "url": "https://github.com/haandol/cognito-kakao-example",
            "title": "haandol/cognito-kakao-example",
            "date_modified": "2022-12-04T08:30:03.000Z",
            "date_published": "2021-01-29T04:23:15.000Z",
            "author": {
                "name": "haandol",
                "url": "https://github.com/haandol"
            }
        },
        {
            "content_html": "<img src=\"https://avatars.githubusercontent.com/u/11066365?u=b53a4544d0ebea15b1625087981cf744aed3ce2e&v=4\" width=\"64\" height=\"64\" alt=\"\"/><br/><div></div>",
            "url": "https://github.com/Avarios/AMAZON-OPENSEARCH-COGNITO",
            "title": "Avarios/AMAZON-OPENSEARCH-COGNITO",
            "date_modified": "2022-08-19T10:24:19.000Z",
            "date_published": "2022-08-05T09:23:26.000Z",
            "author": {
                "name": "Avarios",
                "url": "https://github.com/Avarios"
            }
        },
        {
            "content_html": "<img src=\"https://avatars.githubusercontent.com/u/703354?v=4\" width=\"64\" height=\"64\" alt=\"\"/><br/><div>CloudFront authorization with Cognito for CDK</div>",
            "url": "https://github.com/henrist/cdk-cloudfront-auth",
            "title": "henrist/cdk-cloudfront-auth: CloudFront authorization with Cognito for CDK",
            "date_modified": "2022-12-01T17:42:50.000Z",
            "date_published": "2020-07-11T01:58:54.000Z",
            "author": {
                "name": "henrist",
                "url": "https://github.com/henrist"
            }
        },
        {
            "content_html": "<img src=\"https://avatars.githubusercontent.com/u/33866489?u=88f700fcd3c46e601fec91009e3491ddd911a8b1&v=4\" width=\"64\" height=\"64\" alt=\"\"/><br/><div>backend of bicibici a shared bike system app made using AWS services (Lambda, DynamoDB)</div>",
            "url": "https://github.com/merRen22/backend_bicibici",
            "title": "merRen22/backend_bicibici: backend of bicibici a shared bike system app made using AWS services (Lambda, DynamoDB)",
            "date_modified": "2022-12-04T03:31:13.000Z",
            "date_published": "2019-07-16T04:06:51.000Z",
            "author": {
                "name": "merRen22",
                "url": "https://github.com/merRen22"
            }
        },
        {
            "content_html": "<img src=\"https://avatars.githubusercontent.com/u/70639374?v=4\" width=\"64\" height=\"64\" alt=\"\"/><br/><div></div>",
            "url": "https://github.com/Planet-Source-Code/cognito-external-ip-grabber__1-12240",
            "title": "Planet-Source-Code/cognito-external-ip-grabber__1-12240",
            "date_modified": "2022-12-03T13:58:05.000Z",
            "date_published": "2020-09-22T21:29:05.000Z",
            "author": {
                "name": "Planet-Source-Code",
                "url": "https://github.com/Planet-Source-Code"
            }
        },
        {
            "content_html": "<img src=\"https://avatars.githubusercontent.com/u/110761021?v=4\" width=\"64\" height=\"64\" alt=\"\"/><br/><div>Building a Serverless Web Application with AWS Lambda, Amazon API Gateway, AWS Amplify, Amazon DynamoDB, and Amazon Cognito</div>",
            "url": "https://github.com/Olise756/Aws-Project",
            "title": "Olise756/Aws-Project: Building a Serverless Web Application with AWS Lambda, Amazon API Gateway, AWS Amplify, Amazon DynamoDB, and Amazon Cognito",
            "date_modified": "2022-12-02T19:13:21.000Z",
            "date_published": "2022-12-02T17:43:53.000Z",
            "author": {
                "name": "Olise756",
                "url": "https://github.com/Olise756"
            }
        },
        {
            "content_html": "<img src=\"https://avatars.githubusercontent.com/u/25897113?u=ae51a68aaee7975edc5ea08ac9a5f62eb4c03bd4&v=4\" width=\"64\" height=\"64\" alt=\"\"/><br/><div></div>",
            "url": "https://github.com/marlkiller/aws-cognito-website",
            "title": "marlkiller/aws-cognito-website",
            "date_modified": "2022-12-02T12:24:25.000Z",
            "date_published": "2022-12-02T12:15:22.000Z",
            "author": {
                "name": "marlkiller",
                "url": "https://github.com/marlkiller"
            }
        },
        {
            "content_html": "<img src=\"https://avatars.githubusercontent.com/u/94876538?u=124b475932618a042a0913cf214a9460db1a4635&v=4\" width=\"64\" height=\"64\" alt=\"\"/><br/><div></div>",
            "url": "https://github.com/baskiaiml/angular-amplify-cognito-updated",
            "title": "baskiaiml/angular-amplify-cognito-updated",
            "date_modified": "2022-11-26T02:49:23.000Z",
            "date_published": "2022-11-26T02:43:02.000Z",
            "author": {
                "name": "baskiaiml",
                "url": "https://github.com/baskiaiml"
            }
        },
        {
            "content_html": "<img src=\"https://avatars.githubusercontent.com/u/108037818?v=4\" width=\"64\" height=\"64\" alt=\"\"/><br/><div>A simple demo CLI app that logs into cognito in dart</div>",
            "url": "https://github.com/amigos-dev/dart_cognito_login_cli",
            "title": "amigos-dev/dart_cognito_login_cli: A simple demo CLI app that logs into cognito in dart",
            "date_modified": "2022-11-23T01:49:10.000Z",
            "date_published": "2022-11-22T22:43:05.000Z",
            "author": {
                "name": "amigos-dev",
                "url": "https://github.com/amigos-dev"
            }
        },
        {
            "content_html": "<img src=\"https://avatars.githubusercontent.com/u/37575408?u=61cf90946c58ab7979b5176758b1a06513d6c48b&v=4\" width=\"64\" height=\"64\" alt=\"\"/><br/><div>login</div>",
            "url": "https://github.com/tktcorporation/cognito-test",
            "title": "tktcorporation/cognito-test: login",
            "date_modified": "2022-12-03T12:18:14.000Z",
            "date_published": "2019-05-16T09:08:17.000Z",
            "author": {
                "name": "tktcorporation",
                "url": "https://github.com/tktcorporation"
            }
        },
        {
            "content_html": "<img src=\"https://avatars.githubusercontent.com/u/52019090?v=4\" width=\"64\" height=\"64\" alt=\"\"/><br/><div>Bishop - Cognito User Manager</div>",
            "url": "https://github.com/sylvesterllc/bishop",
            "title": "sylvesterllc/bishop: Bishop - Cognito User Manager",
            "date_modified": "2022-11-27T23:49:57.000Z",
            "date_published": "2022-11-27T23:49:53.000Z",
            "author": {
                "name": "sylvesterllc",
                "url": "https://github.com/sylvesterllc"
            }
        },
        {
            "content_html": "<img src=\"https://avatars.githubusercontent.com/u/8931462?v=4\" width=\"64\" height=\"64\" alt=\"\"/><br/><div>This project is a simple template for getting started with a React app that has SSO configured using Cognito's SAML interface</div>",
            "url": "https://github.com/aws-samples/amazon-cognito-saml-idp",
            "title": "aws-samples/amazon-cognito-saml-idp: This project is a simple template for getting started with a React app that has SSO configured using Cognito's SAML interface",
            "date_modified": "2022-12-03T01:44:57.000Z",
            "date_published": "2022-07-21T20:09:22.000Z",
            "author": {
                "name": "aws-samples",
                "url": "https://github.com/aws-samples"
            }
        },
        {
            "content_html": "<img src=\"https://avatars.githubusercontent.com/u/107164814?v=4\" width=\"64\" height=\"64\" alt=\"\"/><br/><div>A team project to build an Inventory Management System for three user groups: corporate users, store managers, and customers. Technologies include: react (front-end), AWS lambda/API Gateway (for back-end), AWS RDS Database/MySQL, AWS Amplify/Cognito for authentication services. S3-hosted static URL is included below.</div>",
            "url": "https://github.com/MinhHangwpi/CS509-Inventory-Management-System",
            "title": "MinhHangwpi/CS509-Inventory-Management-System: A team project to build an Inventory Management System for three user groups: corporate users, store managers, and customers. Technologies include: react (front-end), AWS lambda/API Gateway (for back-end), AWS RDS Database/MySQL, AWS Amplify/Cognito for authentication services. S3-hosted static URL is included below.",
            "date_modified": "2022-12-03T01:28:32.000Z",
            "date_published": "2022-12-03T01:06:22.000Z",
            "author": {
                "name": "MinhHangwpi",
                "url": "https://github.com/MinhHangwpi"
            }
        }
    ]
}