{
    "version": "https://jsonfeed.org/version/1",
    "title": "Serverless repositories",
    "home_page_url": "https://github.com/search?o=desc&q=serverless+language%3Ajavascript+language%3Atypescript+sort%3Aupdated-desc&s=updated&type=Repositories",
    "feed_url": "https://davidwells.github.io/github-search-rss/serverless-javascript-repo.json",
    "description": "Serverless repositories on GitHub",
    "items": [
        {
            "content_html": "<img src=\"https://avatars.githubusercontent.com/u/379814?u=6d486f21f7e5e4fdf3931a192fe1f5f2b28c244e&v=4\" width=\"64\" height=\"64\" alt=\"\"/><br/><div>Streamlink as a Serverless Service</div>",
            "url": "https://github.com/mrgrain/streamlink-serverless",
            "title": "mrgrain/streamlink-serverless: Streamlink as a Serverless Service",
            "date_modified": "2022-12-17T21:40:19.000Z",
            "date_published": "2022-09-11T22:02:40.000Z",
            "author": {
                "name": "mrgrain",
                "url": "https://github.com/mrgrain"
            }
        },
        {
            "content_html": "<img src=\"https://avatars.githubusercontent.com/u/217931?u=1b511633d1d6a911150d495ca401032f250a4994&v=4\" width=\"64\" height=\"64\" alt=\"\"/><br/><div>Dashboard for all feature branches - linking to the deployed/running in docker containers  and showing their states. Live Version:</div>",
            "url": "https://github.com/lowsky/gh-dashboard-relay",
            "title": "lowsky/gh-dashboard-relay: Dashboard for all feature branches - linking to the deployed/running in docker containers  and showing their states. Live Version:",
            "date_modified": "2022-11-21T20:26:06.000Z",
            "date_published": "2015-03-27T11:24:17.000Z",
            "author": {
                "name": "lowsky",
                "url": "https://github.com/lowsky"
            }
        },
        {
            "content_html": "<img src=\"https://avatars.githubusercontent.com/u/43639?u=b15333a3009c02afc3692d3669b83af798a90b6c&v=4\" width=\"64\" height=\"64\" alt=\"\"/><br/><div>Receive verified Shopify order creation webhooks and make Trello cards out of them.</div>",
            "url": "https://github.com/hectcastro/shopify-trello-bridge",
            "title": "hectcastro/shopify-trello-bridge: Receive verified Shopify order creation webhooks and make Trello cards out of them.",
            "date_modified": "2022-12-08T00:11:31.000Z",
            "date_published": "2021-05-31T01:40:31.000Z",
            "author": {
                "name": "hectcastro",
                "url": "https://github.com/hectcastro"
            }
        },
        {
            "content_html": "<img src=\"https://avatars.githubusercontent.com/u/278432?u=dd437e74427fddade6146e47ada192213310eff2&v=4\" width=\"64\" height=\"64\" alt=\"\"/><br/><div>CDK Constructs for Serverless Demo</div>",
            "url": "https://github.com/pahud/cdk-simple-serverless",
            "title": "pahud/cdk-simple-serverless: CDK Constructs for Serverless Demo",
            "date_modified": "2022-11-03T00:19:11.000Z",
            "date_published": "2021-11-08T13:20:41.000Z",
            "author": {
                "name": "pahud",
                "url": "https://github.com/pahud"
            }
        },
        {
            "content_html": "<img src=\"https://avatars.githubusercontent.com/u/118717435?v=4\" width=\"64\" height=\"64\" alt=\"\"/><br/><div>a lightweight cms self-hosted on cloudflare, for podcasts, blogs, photos, videos, documents, and curated urls.</div>",
            "url": "https://github.com/microfeed/microfeed",
            "title": "microfeed/microfeed: a lightweight cms self-hosted on cloudflare, for podcasts, blogs, photos, videos, documents, and curated urls.",
            "date_modified": "2022-12-29T00:15:54.000Z",
            "date_published": "2020-05-25T03:50:26.000Z",
            "author": {
                "name": "microfeed",
                "url": "https://github.com/microfeed"
            }
        },
        {
            "content_html": "<img src=\"https://avatars.githubusercontent.com/u/114664568?v=4\" width=\"64\" height=\"64\" alt=\"\"/><br/><div><g-emoji class=\"g-emoji\" alias=\"atom_symbol\" fallback-src=\"https://github.githubassets.com/images/icons/emoji/unicode/269b.png\">⚛️</g-emoji> Headless full-stack framework for Artisans. Develop modern clouds, apps &amp; framework-agnostic libraries, faster.</div>",
            "url": "https://github.com/stacksjs/stacks",
            "title": "stacksjs/stacks: ⚛️ Headless full-stack framework for Artisans. Develop modern clouds, apps & framework-agnostic libraries, faster.",
            "date_modified": "2022-12-21T18:41:40.000Z",
            "date_published": "2022-04-26T05:46:57.000Z",
            "author": {
                "name": "stacksjs",
                "url": "https://github.com/stacksjs"
            }
        },
        {
            "content_html": "<img src=\"https://avatars.githubusercontent.com/u/354444?v=4\" width=\"64\" height=\"64\" alt=\"\"/><br/><div>run a remote transformation</div>",
            "url": "https://github.com/rebeccapeltz/cld-remote-serverless",
            "title": "rebeccapeltz/cld-remote-serverless: run a remote transformation",
            "date_modified": "2022-12-27T20:04:43.000Z",
            "date_published": "2022-12-27T20:04:01.000Z",
            "author": {
                "name": "rebeccapeltz",
                "url": "https://github.com/rebeccapeltz"
            }
        },
        {
            "content_html": "<img src=\"https://avatars.githubusercontent.com/u/6833443?u=fab58c6319431eebaf1852f6472c90f4bddc43c8&v=4\" width=\"64\" height=\"64\" alt=\"\"/><br/><div>Serverless wiki with Markdown syntax</div>",
            "url": "https://github.com/dominik-zeglen/md-wiki",
            "title": "dominik-zeglen/md-wiki: Serverless wiki with Markdown syntax",
            "date_modified": "2022-10-29T17:31:56.000Z",
            "date_published": "2022-10-29T17:31:08.000Z",
            "author": {
                "name": "dominik-zeglen",
                "url": "https://github.com/dominik-zeglen"
            }
        },
        {
            "content_html": "<img src=\"https://avatars.githubusercontent.com/u/90267436?u=c686c3199c2c871efe86d4feea39eb05c5bd864b&v=4\" width=\"64\" height=\"64\" alt=\"\"/><br/><div>Tutorial from LinkedIn Learning by Brett McLaughlin</div>",
            "url": "https://github.com/jonesong1/serverlessAws",
            "title": "jonesong1/serverlessAws: Tutorial from LinkedIn Learning by Brett McLaughlin",
            "date_modified": "2022-12-27T19:01:12.000Z",
            "date_published": "2022-12-27T18:00:14.000Z",
            "author": {
                "name": "jonesong1",
                "url": "https://github.com/jonesong1"
            }
        },
        {
            "content_html": "<img src=\"https://avatars.githubusercontent.com/u/75994572?u=1c21e2139c0ca225832fe48c0e29216b3bdd861a&v=4\" width=\"64\" height=\"64\" alt=\"\"/><br/><div>serverless lambda function using express and typescript with CRUD operation with Auth, using AWS dynamoDB and AWS cognito</div>",
            "url": "https://github.com/bobbykim89/poc-cookbook-api",
            "title": "bobbykim89/poc-cookbook-api: serverless lambda function using express and typescript with CRUD operation with Auth, using AWS dynamoDB and AWS cognito",
            "date_modified": "2022-12-27T23:55:29.000Z",
            "date_published": "2022-12-27T23:53:06.000Z",
            "author": {
                "name": "bobbykim89",
                "url": "https://github.com/bobbykim89"
            }
        },
        {
            "content_html": "<img src=\"https://avatars.githubusercontent.com/u/72308571?v=4\" width=\"64\" height=\"64\" alt=\"\"/><br/><div><g-emoji class=\"g-emoji\" alias=\"cloud\" fallback-src=\"https://github.githubassets.com/images/icons/emoji/unicode/2601.png\">☁️</g-emoji> CDK constructs for interacting with Buttonize</div>",
            "url": "https://github.com/buttonize/buttonize-cdk",
            "title": "buttonize/buttonize-cdk: ☁️ CDK constructs for interacting with Buttonize",
            "date_modified": "2022-10-23T17:02:24.000Z",
            "date_published": "2022-02-08T18:45:15.000Z",
            "author": {
                "name": "buttonize",
                "url": "https://github.com/buttonize"
            }
        },
        {
            "content_html": "<img src=\"https://avatars.githubusercontent.com/u/16259639?v=4\" width=\"64\" height=\"64\" alt=\"\"/><br/><div>Serverless application for submitting and managing submissions to the US Covid Atlas oral histories project.</div>",
            "url": "https://github.com/GeoDaCenter/covid-histories",
            "title": "GeoDaCenter/covid-histories: Serverless application for submitting and managing submissions to the US Covid Atlas oral histories project.",
            "date_modified": "2022-12-15T00:13:13.000Z",
            "date_published": "2022-04-11T20:15:24.000Z",
            "author": {
                "name": "GeoDaCenter",
                "url": "https://github.com/GeoDaCenter"
            }
        },
        {
            "content_html": "<img src=\"https://avatars.githubusercontent.com/u/1941990?v=4\" width=\"64\" height=\"64\" alt=\"\"/><br/><div>Serverless functions that post a weekly and/or daily summary of leave record in ProjectWorks into Slack</div>",
            "url": "https://github.com/ackama/projectworks-leave-notifications",
            "title": "ackama/projectworks-leave-notifications: Serverless functions that post a weekly and/or daily summary of leave record in ProjectWorks into Slack",
            "date_modified": "2022-12-28T23:14:11.000Z",
            "date_published": "2020-11-04T01:17:39.000Z",
            "author": {
                "name": "ackama",
                "url": "https://github.com/ackama"
            }
        },
        {
            "content_html": "<img src=\"https://avatars.githubusercontent.com/u/4739705?u=c1d8cc8de326fb610030989a5e3c372d39d9a84a&v=4\" width=\"64\" height=\"64\" alt=\"\"/><br/><div></div>",
            "url": "https://github.com/henriklippke/serverless-dynamodb-gsi",
            "title": "henriklippke/serverless-dynamodb-gsi",
            "date_modified": "2022-12-28T22:29:12.000Z",
            "date_published": "2022-12-28T22:16:18.000Z",
            "author": {
                "name": "henriklippke",
                "url": "https://github.com/henriklippke"
            }
        },
        {
            "content_html": "<img src=\"https://avatars.githubusercontent.com/u/24557830?v=4\" width=\"64\" height=\"64\" alt=\"\"/><br/><div>Serverless services for pet api. Pet is an adoption platform where you can adop your next friend. </div>",
            "url": "https://github.com/hjtigua/pets",
            "title": "hjtigua/pets: Serverless services for pet api. Pet is an adoption platform where you can adop your next friend. ",
            "date_modified": "2022-12-23T23:59:19.000Z",
            "date_published": "2022-12-23T23:58:12.000Z",
            "author": {
                "name": "hjtigua",
                "url": "https://github.com/hjtigua"
            }
        },
        {
            "content_html": "<img src=\"https://avatars.githubusercontent.com/u/8782055?u=72abb64627e32f96d77867a96676fb124a4b8d44&v=4\" width=\"64\" height=\"64\" alt=\"\"/><br/><div>A serverless and offline-first PWA that lets you track your mood</div>",
            "url": "https://github.com/benji6/moodtracker",
            "title": "benji6/moodtracker: A serverless and offline-first PWA that lets you track your mood",
            "date_modified": "2022-12-24T17:51:36.000Z",
            "date_published": "2020-04-07T07:22:55.000Z",
            "author": {
                "name": "benji6",
                "url": "https://github.com/benji6"
            }
        },
        {
            "content_html": "<img src=\"https://avatars.githubusercontent.com/u/25966?u=fd866ec42bdc141a9fe09e9039388f98bf80aa9c&v=4\" width=\"64\" height=\"64\" alt=\"\"/><br/><div>Graphql-WS compatible Lambda Powered Subscriptions</div>",
            "url": "https://github.com/reconbot/graphql-lambda-subscriptions",
            "title": "reconbot/graphql-lambda-subscriptions: Graphql-WS compatible Lambda Powered Subscriptions",
            "date_modified": "2022-12-24T14:14:12.000Z",
            "date_published": "2021-08-06T20:41:47.000Z",
            "author": {
                "name": "reconbot",
                "url": "https://github.com/reconbot"
            }
        },
        {
            "content_html": "<img src=\"https://avatars.githubusercontent.com/u/64281914?v=4\" width=\"64\" height=\"64\" alt=\"\"/><br/><div>Serverless API Gateway for GraphQL, REST, gRPC, Kafka and more with a focus on API Composition &amp; Integration.</div>",
            "url": "https://github.com/wundergraph/wundergraph",
            "title": "wundergraph/wundergraph: Serverless API Gateway for GraphQL, REST, gRPC, Kafka and more with a focus on API Composition & Integration.",
            "date_modified": "2022-12-28T05:47:56.000Z",
            "date_published": "2022-05-24T14:45:44.000Z",
            "author": {
                "name": "wundergraph",
                "url": "https://github.com/wundergraph"
            }
        },
        {
            "content_html": "<img src=\"https://avatars.githubusercontent.com/u/43791938?v=4\" width=\"64\" height=\"64\" alt=\"\"/><br/><div>Connect APIs, remarkably fast.  Free for developers.</div>",
            "url": "https://github.com/PipedreamHQ/pipedream",
            "title": "PipedreamHQ/pipedream: Connect APIs, remarkably fast.  Free for developers.",
            "date_modified": "2022-12-28T23:39:12.000Z",
            "date_published": "2020-01-22T00:28:31.000Z",
            "author": {
                "name": "PipedreamHQ",
                "url": "https://github.com/PipedreamHQ"
            }
        },
        {
            "content_html": "<img src=\"https://avatars.githubusercontent.com/u/106432792?v=4\" width=\"64\" height=\"64\" alt=\"\"/><br/><div>Deploy Serverless Functions at the Edge. Current status: Dev</div>",
            "url": "https://github.com/lagonapp/lagon",
            "title": "lagonapp/lagon: Deploy Serverless Functions at the Edge. Current status: Dev",
            "date_modified": "2022-12-28T23:16:05.000Z",
            "date_published": "2022-06-20T06:08:05.000Z",
            "author": {
                "name": "lagonapp",
                "url": "https://github.com/lagonapp"
            }
        }
    ]
}