{
    "version": "https://jsonfeed.org/version/1",
    "title": "Serverless repositories",
    "home_page_url": "https://github.com/search?o=desc&q=serverless+language%3Ajavascript+language%3Atypescript+sort%3Aupdated-desc&s=updated&type=Repositories",
    "feed_url": "https://davidwells.github.io/github-search-rss/serverless-javascript-repo.json",
    "description": "Serverless repositories on GitHub",
    "items": [
        {
            "content_html": "<img src=\"https://avatars.githubusercontent.com/u/99120681?v=4\" width=\"64\" height=\"64\" alt=\"\"/><br/><div>Learn Modern Full Stack Web 2 Development using Typescript, Next.js, Tailwind CSS, tRPC, Prisma, Contentful, and Strapi.</div>",
            "url": "https://github.com/panaverse/learn-nextjs",
            "title": "panaverse/learn-nextjs: Learn Modern Full Stack Web 2 Development using Typescript, Next.js, Tailwind CSS, tRPC, Prisma, Contentful, and Strapi.",
            "date_modified": "2023-02-28T12:11:54.000Z",
            "date_published": "2022-06-17T05:09:34.000Z",
            "author": {
                "name": "panaverse",
                "url": "https://github.com/panaverse"
            }
        },
        {
            "content_html": "<img src=\"https://avatars.githubusercontent.com/u/33217104?v=4\" width=\"64\" height=\"64\" alt=\"\"/><br/><div>A reference implementation of a serverless backend for an IoT product developed using AWS CDK in TypeScript.</div>",
            "url": "https://github.com/NordicSemiconductor/asset-tracker-cloud-aws-js",
            "title": "NordicSemiconductor/asset-tracker-cloud-aws-js: A reference implementation of a serverless backend for an IoT product developed using AWS CDK in TypeScript.",
            "date_modified": "2023-01-31T18:42:34.000Z",
            "date_published": "2021-01-26T15:44:54.000Z",
            "author": {
                "name": "NordicSemiconductor",
                "url": "https://github.com/NordicSemiconductor"
            }
        },
        {
            "content_html": "<img src=\"https://avatars.githubusercontent.com/u/379814?u=6d486f21f7e5e4fdf3931a192fe1f5f2b28c244e&v=4\" width=\"64\" height=\"64\" alt=\"\"/><br/><div>Streamlink as a Serverless Service</div>",
            "url": "https://github.com/mrgrain/streamlink-serverless",
            "title": "mrgrain/streamlink-serverless: Streamlink as a Serverless Service",
            "date_modified": "2023-02-18T17:05:02.000Z",
            "date_published": "2022-09-11T22:02:40.000Z",
            "author": {
                "name": "mrgrain",
                "url": "https://github.com/mrgrain"
            }
        },
        {
            "content_html": "<img src=\"https://avatars.githubusercontent.com/u/88006947?u=341082d772b9b891c7457d995d5df1d5fc1f103d&v=4\" width=\"64\" height=\"64\" alt=\"\"/><br/><div>Trying out serverless with aws</div>",
            "url": "https://github.com/Dean998/serverless-run",
            "title": "Dean998/serverless-run: Trying out serverless with aws",
            "date_modified": "2023-02-25T23:21:01.000Z",
            "date_published": "2023-02-22T21:14:09.000Z",
            "author": {
                "name": "Dean998",
                "url": "https://github.com/Dean998"
            }
        },
        {
            "content_html": "<img src=\"https://avatars.githubusercontent.com/u/278432?u=dd437e74427fddade6146e47ada192213310eff2&v=4\" width=\"64\" height=\"64\" alt=\"\"/><br/><div>CDK Constructs for Serverless Demo</div>",
            "url": "https://github.com/pahud/cdk-simple-serverless",
            "title": "pahud/cdk-simple-serverless: CDK Constructs for Serverless Demo",
            "date_modified": "2023-01-31T19:16:36.000Z",
            "date_published": "2021-11-08T13:20:41.000Z",
            "author": {
                "name": "pahud",
                "url": "https://github.com/pahud"
            }
        },
        {
            "content_html": "<img src=\"https://avatars.githubusercontent.com/u/12616554?u=e7cd16f0789636f5ab1d5d6323aa295e3d8d248a&v=4\" width=\"64\" height=\"64\" alt=\"\"/><br/><div>A workflow that hits a weather API and updates a website to show current conditions</div>",
            "url": "https://github.com/deeheber/weather-site",
            "title": "deeheber/weather-site: A workflow that hits a weather API and updates a website to show current conditions",
            "date_modified": "2023-02-26T22:08:50.000Z",
            "date_published": "2023-02-25T23:40:45.000Z",
            "author": {
                "name": "deeheber",
                "url": "https://github.com/deeheber"
            }
        },
        {
            "content_html": "<img src=\"https://avatars.githubusercontent.com/u/41077760?v=4\" width=\"64\" height=\"64\" alt=\"\"/><br/><div>The AWS Amplify CLI is a toolchain for simplifying serverless web and mobile development.</div>",
            "url": "https://github.com/aws-amplify/amplify-cli",
            "title": "aws-amplify/amplify-cli: The AWS Amplify CLI is a toolchain for simplifying serverless web and mobile development.",
            "date_modified": "2023-02-27T23:44:31.000Z",
            "date_published": "2018-08-23T16:33:10.000Z",
            "author": {
                "name": "aws-amplify",
                "url": "https://github.com/aws-amplify"
            }
        },
        {
            "content_html": "<img src=\"https://avatars.githubusercontent.com/u/41077760?v=4\" width=\"64\" height=\"64\" alt=\"\"/><br/><div> The AWS Amplify CLI is a toolchain for simplifying serverless web and mobile development. This plugin provides functionality for the API category, allowing for the creation and management of GraphQL and REST based backends for your amplify project.</div>",
            "url": "https://github.com/aws-amplify/amplify-category-api",
            "title": "aws-amplify/amplify-category-api:  The AWS Amplify CLI is a toolchain for simplifying serverless web and mobile development. This plugin provides functionality for the API category, allowing for the creation and management of GraphQL and REST based backends for your amplify project.",
            "date_modified": "2023-02-27T18:03:17.000Z",
            "date_published": "2022-03-10T16:36:09.000Z",
            "author": {
                "name": "aws-amplify",
                "url": "https://github.com/aws-amplify"
            }
        },
        {
            "content_html": "<img src=\"https://avatars.githubusercontent.com/u/111129354?v=4\" width=\"64\" height=\"64\" alt=\"\"/><br/><div>Making Event Sourcing easy <g-emoji class=\"g-emoji\" alias=\"sunglasses\" fallback-src=\"https://github.githubassets.com/images/icons/emoji/unicode/1f60e.png\">😎</g-emoji></div>",
            "url": "https://github.com/castore-dev/castore",
            "title": "castore-dev/castore: Making Event Sourcing easy 😎",
            "date_modified": "2023-02-26T10:23:39.000Z",
            "date_published": "2022-08-12T12:40:09.000Z",
            "author": {
                "name": "castore-dev",
                "url": "https://github.com/castore-dev"
            }
        },
        {
            "content_html": "<img src=\"https://avatars.githubusercontent.com/u/19890291?u=48aeeb3985fb16f7dee2b827d4be962ccd421f1e&v=4\" width=\"64\" height=\"64\" alt=\"\"/><br/><div>A online mobile RPG game engine and infrastructure as code monorepo. Built using Unreal 5, AWS CDKv2, and Typescript.</div>",
            "url": "https://github.com/hxtree/cats-cradle",
            "title": "hxtree/cats-cradle: A online mobile RPG game engine and infrastructure as code monorepo. Built using Unreal 5, AWS CDKv2, and Typescript.",
            "date_modified": "2023-02-19T06:26:54.000Z",
            "date_published": "2021-12-16T04:06:13.000Z",
            "author": {
                "name": "hxtree",
                "url": "https://github.com/hxtree"
            }
        },
        {
            "content_html": "<img src=\"https://avatars.githubusercontent.com/u/74420131?v=4\" width=\"64\" height=\"64\" alt=\"\"/><br/><div>Your one-stop-shop to try Xata out. From packages to apps, whatever you need to get started.</div>",
            "url": "https://github.com/xataio/examples",
            "title": "xataio/examples: Your one-stop-shop to try Xata out. From packages to apps, whatever you need to get started.",
            "date_modified": "2023-02-28T13:08:39.000Z",
            "date_published": "2022-03-15T11:57:17.000Z",
            "author": {
                "name": "xataio",
                "url": "https://github.com/xataio"
            }
        },
        {
            "content_html": "<img src=\"https://avatars.githubusercontent.com/u/37520021?v=4\" width=\"64\" height=\"64\" alt=\"\"/><br/><div>Sample REST API demo for simple todo app</div>",
            "url": "https://github.com/rioastamal-examples/serverless-todo-express-api",
            "title": "rioastamal-examples/serverless-todo-express-api: Sample REST API demo for simple todo app",
            "date_modified": "2023-02-27T13:46:37.000Z",
            "date_published": "2023-02-25T23:48:39.000Z",
            "author": {
                "name": "rioastamal-examples",
                "url": "https://github.com/rioastamal-examples"
            }
        },
        {
            "content_html": "<img src=\"https://avatars.githubusercontent.com/u/19392244?u=91f8b05dc4601bf28e12f5d51a5c26cb7268b66d&v=4\" width=\"64\" height=\"64\" alt=\"\"/><br/><div></div>",
            "url": "https://github.com/Hilyas68/Serverless-framework-todo-app",
            "title": "Hilyas68/Serverless-framework-todo-app",
            "date_modified": "2023-02-28T17:22:40.000Z",
            "date_published": "2023-02-28T15:42:41.000Z",
            "author": {
                "name": "Hilyas68",
                "url": "https://github.com/Hilyas68"
            }
        },
        {
            "content_html": "<img src=\"https://avatars.githubusercontent.com/u/114664568?v=4\" width=\"64\" height=\"64\" alt=\"\"/><br/><div><g-emoji class=\"g-emoji\" alias=\"atom_symbol\" fallback-src=\"https://github.githubassets.com/images/icons/emoji/unicode/269b.png\">⚛️</g-emoji> Headless full-stack framework for Artisans. Develop modern clouds, apps &amp; framework-agnostic libraries, faster.</div>",
            "url": "https://github.com/stacksjs/stacks",
            "title": "stacksjs/stacks: ⚛️ Headless full-stack framework for Artisans. Develop modern clouds, apps & framework-agnostic libraries, faster.",
            "date_modified": "2023-02-25T12:51:55.000Z",
            "date_published": "2022-04-26T05:46:57.000Z",
            "author": {
                "name": "stacksjs",
                "url": "https://github.com/stacksjs"
            }
        },
        {
            "content_html": "<img src=\"https://avatars.githubusercontent.com/u/25966?u=fd866ec42bdc141a9fe09e9039388f98bf80aa9c&v=4\" width=\"64\" height=\"64\" alt=\"\"/><br/><div>Graphql-WS compatible Lambda Powered Subscriptions</div>",
            "url": "https://github.com/reconbot/graphql-lambda-subscriptions",
            "title": "reconbot/graphql-lambda-subscriptions: Graphql-WS compatible Lambda Powered Subscriptions",
            "date_modified": "2023-02-27T16:26:32.000Z",
            "date_published": "2021-08-06T20:41:47.000Z",
            "author": {
                "name": "reconbot",
                "url": "https://github.com/reconbot"
            }
        },
        {
            "content_html": "<img src=\"https://avatars.githubusercontent.com/u/33217104?v=4\" width=\"64\" height=\"64\" alt=\"\"/><br/><div>Implementation of a test-runner for end-to-end tests of cloud-native applications using Gherkin features.</div>",
            "url": "https://github.com/NordicSemiconductor/cloud-e2e-bdd-test-runner-js",
            "title": "NordicSemiconductor/cloud-e2e-bdd-test-runner-js: Implementation of a test-runner for end-to-end tests of cloud-native applications using Gherkin features.",
            "date_modified": "2023-01-31T18:42:34.000Z",
            "date_published": "2021-01-26T15:47:17.000Z",
            "author": {
                "name": "NordicSemiconductor",
                "url": "https://github.com/NordicSemiconductor"
            }
        },
        {
            "content_html": "<img src=\"https://avatars.githubusercontent.com/u/66570915?v=4\" width=\"64\" height=\"64\" alt=\"\"/><br/><div><g-emoji class=\"g-emoji\" alias=\"boom\" fallback-src=\"https://github.githubassets.com/images/icons/emoji/unicode/1f4a5.png\">💥</g-emoji> SST makes it easy to build full-stack serverless apps.</div>",
            "url": "https://github.com/serverless-stack/sst",
            "title": "serverless-stack/sst: 💥 SST makes it easy to build full-stack serverless apps.",
            "date_modified": "2023-02-28T23:15:12.000Z",
            "date_published": "2020-08-04T20:28:14.000Z",
            "author": {
                "name": "serverless-stack",
                "url": "https://github.com/serverless-stack"
            }
        },
        {
            "content_html": "<img src=\"https://avatars.githubusercontent.com/u/126543657?v=4\" width=\"64\" height=\"64\" alt=\"\"/><br/><div></div>",
            "url": "https://github.com/230109-capstone/serverless-sam-backend",
            "title": "230109-capstone/serverless-sam-backend",
            "date_modified": "2023-02-28T21:18:29.000Z",
            "date_published": "2023-02-28T20:56:59.000Z",
            "author": {
                "name": "230109-capstone",
                "url": "https://github.com/230109-capstone"
            }
        },
        {
            "content_html": "<img src=\"https://avatars.githubusercontent.com/u/22839396?v=4\" width=\"64\" height=\"64\" alt=\"\"/><br/><div>Conference networking tool built with Angular PWA and Serverless + AWS AppSync</div>",
            "url": "https://github.com/thisdot/lets-chat-with",
            "title": "thisdot/lets-chat-with: Conference networking tool built with Angular PWA and Serverless + AWS AppSync",
            "date_modified": "2023-02-21T02:06:13.000Z",
            "date_published": "2023-02-09T22:24:43.000Z",
            "author": {
                "name": "thisdot",
                "url": "https://github.com/thisdot"
            }
        },
        {
            "content_html": "<img src=\"https://avatars.githubusercontent.com/u/3209407?v=4\" width=\"64\" height=\"64\" alt=\"\"/><br/><div>MINT App</div>",
            "url": "https://github.com/CMSgov/mint-app",
            "title": "CMSgov/mint-app: MINT App",
            "date_modified": "2023-02-12T22:24:28.000Z",
            "date_published": "2022-03-07T18:07:06.000Z",
            "author": {
                "name": "CMSgov",
                "url": "https://github.com/CMSgov"
            }
        }
    ]
}